README.rst
setup.cfg
setup.py
django_robokassa_merchant.egg-info/PKG-INFO
django_robokassa_merchant.egg-info/SOURCES.txt
django_robokassa_merchant.egg-info/dependency_links.txt
django_robokassa_merchant.egg-info/top_level.txt
robokassa_merchant/__init__.py
robokassa_merchant/admin.py
robokassa_merchant/apps.py
robokassa_merchant/conf.py
robokassa_merchant/forms.py
robokassa_merchant/models.py
robokassa_merchant/options.py
robokassa_merchant/signals.py
robokassa_merchant/tests.py
robokassa_merchant/utils.py
robokassa_merchant/views.py
robokassa_merchant/migrations/0001_initial.py
robokassa_merchant/migrations/__init__.py
tests/test_app/__init__.py
tests/test_app/apps.py
tests/test_app/models.py
tests/test_app/tests.py
tests/test_app/urls.py
tests/test_app/views.py
tests/test_app/migrations/0001_initial.py
tests/test_app/migrations/__init__.py