Metadata-Version: 1.1
Name: django-robokassa-merchant
Version: 0.2
Summary: Django Application for Robokassa.ru
Home-page: https://github.com/DirectlineDev/django-robokassa-merchant
Author: Anton Kuzmichev
Author-email: assargin@gmail.com
License: MIT License
Download-URL: https://github.com/DirectlineDev/django-robokassa-merchant/archive/master.zip
Keywords: django,robokassa,merchant
Platform: UNKNOWN
Classifier: Development Status :: 4 - Beta
Classifier: Framework :: Django
Classifier: Framework :: Django :: 1.8
Classifier: Framework :: Django :: 1.9
Classifier: Intended Audience :: Developers
Classifier: License :: OSI Approved :: MIT License
Classifier: Operating System :: OS Independent
Classifier: Programming Language :: Python
Classifier: Programming Language :: Python :: 2
Classifier: Programming Language :: Python :: 2.7
Classifier: Programming Language :: Python :: 3
Classifier: Programming Language :: Python :: 3.4
